README.rst
setup.py
cini/__init__.py
cini/models.py
cini.egg-info/PKG-INFO
cini.egg-info/SOURCES.txt
cini.egg-info/dependency_links.txt
cini.egg-info/top_level.txt