Metadata-Version: 1.0
Name: cini
Version: 0.2.6
Summary: Librería para calcular de forma automática el código de identificación normalizado de instalaciones
Home-page: https://github.com/gisce/cini
Author: GISCE-TI, S.L.
Author-email: devel@gisce.net
License: MIT
Platform: UNKNOWN
